Serializer/DeserializerJSON.py
Serializer/DeserializerXML.py
Serializer/ParserJSON.py
Serializer/ParserXML.py
Serializer/SerializerFactory.py
Serializer/SerializerJSON.py
Serializer/SerializerXML.py
Serializer/__init__.py
Serializer/constants.py
SerializerCHedgie-0.0.1.dist-info/METADATA
SerializerCHedgie-0.0.1.dist-info/WHEEL
SerializerCHedgie-0.0.1.dist-info/top_level.txt
SerializerCHedgie-0.0.1.dist-info/RECORD
