Metadata-Version: 2.1
Name: SerializerCHedgie
Version: 0.0.1
Summary: Python serializer
Author: Yulia Atrashonok
Author-email: <yulia.atrashonok@yandex.ru>
Keywords: python,first package
Classifier: Intended Audience :: Education
Classifier: Programming Language :: Python :: 3
Classifier: Operating System :: OS Independent
